README.rst
setup.py
geox_statistics/__init__.py
geox_statistics/mean.py
geox_statistics.egg-info/PKG-INFO
geox_statistics.egg-info/SOURCES.txt
geox_statistics.egg-info/dependency_links.txt
geox_statistics.egg-info/requires.txt
geox_statistics.egg-info/top_level.txt