Metadata-Version: 1.0
Name: geox-statistics
Version: 0.0.3
Summary: GeoX young academy Python example
Home-page: https://github.com/KDD-OpenSource/geox-young-academy/
Author: UNKNOWN
Author-email: UNKNOWN
License: UNKNOWN
Keywords: data Science,Seminar
Platform: UNKNOWN
